tensorBNN/BNN_functions.py
tensorBNN/__init__.py
tensorBNN/activationFunctions.py
tensorBNN/layer.py
tensorBNN/likelihood.py
tensorBNN/metrics.py
tensorBNN/network.py
tensorBNN/paramAdapter.py
tensorBNN/predictor.py
tensorBNN-0.12.3.dist-info/LICENSE
tensorBNN-0.12.3.dist-info/METADATA
tensorBNN-0.12.3.dist-info/WHEEL
tensorBNN-0.12.3.dist-info/top_level.txt
tensorBNN-0.12.3.dist-info/RECORD
