Metadata-Version: 2.1
Name: tensorBNN
Version: 0.12.3
Summary: A Bayesian Neural Network implementation in TensorFlow
Home-page: https://alpha-davidson.github.io/TensorBNN/
Author: Braden Kronheim
Author-email: brkronheim@davidson.com
License: UNKNOWN
Platform: UNKNOWN
Classifier: Programming Language :: Python :: 3
Classifier: License :: OSI Approved :: MIT License
Requires-Python: <3.8.0
Requires-Dist: emcee (>=3.0.2)
Requires-Dist: scipy (>=1.4.1)
